chembl_miner/__init__.py
chembl_miner/analysis.py
chembl_miner/config.py
chembl_miner/data_preprocessing.py
chembl_miner/data_retrieval.py
chembl_miner/datasets.py
chembl_miner/feature_engineering.py
chembl_miner/machine_learning.py
chembl_miner/utils.py
chembl_miner/fingerprinters/AtomPairs2DFingerprintCount.xml
chembl_miner/fingerprinters/AtomPairs2DFingerprinter.xml
chembl_miner/fingerprinters/EStateFingerprinter.xml
chembl_miner/fingerprinters/ExtendedFingerprinter.xml
chembl_miner/fingerprinters/Fingerprinter.xml
chembl_miner/fingerprinters/GraphOnlyFingerprinter.xml
chembl_miner/fingerprinters/KlekotaRothFingerprintCount.xml
chembl_miner/fingerprinters/KlekotaRothFingerprinter.xml
chembl_miner/fingerprinters/MACCSFingerprinter.xml
chembl_miner/fingerprinters/PubchemFingerprinter.xml
chembl_miner/fingerprinters/SubstructureFingerprintCount.xml
chembl_miner/fingerprinters/SubstructureFingerprinter.xml
chembl_miner-0.1.11.dist-info/licenses/LICENSE
chembl_miner-0.1.11.dist-info/METADATA
chembl_miner-0.1.11.dist-info/WHEEL
chembl_miner-0.1.11.dist-info/top_level.txt
chembl_miner-0.1.11.dist-info/RECORD
